autocoder.py
cli_websocket_client.py
enhanced_main.py
main.py
main_api.py
agents/__init__.py
agents/agent_config.py
agents/base_agent.py
agents/db_expert.py
agents/developer.py
agents/devops_expert.py
agents/mcp_client.py
agents/mcp_client_fastmcp.py
agents/planner.py
agents/tester.py
agents/ui_ux_expert.py
git_integration/__init__.py
git_integration/git_manager.py
memory/__init__.py
memory/project_memory.py
sandbox/__init__.py
sandbox/executor.py
utils/__init__.py
utils/agent_prompts.py
utils/config_loader.py
utils/config_merger.py
utils/config_setup.py
utils/file_handler.py
utils/funny_names.py
utils/logger.py
utils/port_finder.py
utils/provider_validator.py
utils/verify_providers.py
web_interface/__init__.py
web_interface/agent_event_emitter.py
web_interface/app.py
web_interface/auth.py
web_interface/export_manager.py
web_interface/fastapi_routes.py
web_interface/mcp_config.py
web_interface/mcp_servers.yaml
web_interface/message_queue.py
web_interface/object_storage.py
web_interface/routes.py
web_interface/websocket_handler.py
web_interface/websocket_manager.py
web_interface/static/css/heatmap.css
web_interface/static/css/style.css
web_interface/static/js/app.js
web_interface/static/js/heatmap.js
web_interface/static/js/mcp-config.js
web_interface/static/js/task-monitor.js
web_interface/templates/agent_settings.html
web_interface/templates/base.html
web_interface/templates/error.html
web_interface/templates/index.html
web_interface/templates/mcp-config.html
web_interface/templates/new_project.html
web_interface/templates/project_detail.html
web_interface/templates/projects.html
web_interface/templates/task_detail.html
workflow/__init__.py
workflow/orchestrator.py
workflow/state.py
autocoder_ai-2.0.12.dist-info/METADATA
autocoder_ai-2.0.12.dist-info/WHEEL
autocoder_ai-2.0.12.dist-info/entry_points.txt
autocoder_ai-2.0.12.dist-info/top_level.txt
autocoder_ai-2.0.12.dist-info/RECORD
