Metadata-Version: 2.4
Name: autocoder-ai
Version: 2.0.12
Summary: AI-powered multi-agent development platform for autonomous code generation
Author-email: Elad Rave <eladrave@gmail.com>
License-Expression: MIT
Project-URL: Homepage, https://github.com/eladrave/autocoder
Project-URL: Documentation, https://github.com/eladrave/autocoder/wiki
Project-URL: Repository, https://github.com/eladrave/autocoder.git
Project-URL: Bug Tracker, https://github.com/eladrave/autocoder/issues
Classifier: Development Status :: 4 - Beta
Classifier: Intended Audience :: Developers
Classifier: Topic :: Software Development :: Code Generators
Classifier: Topic :: Software Development :: Libraries :: Application Frameworks
Classifier: Programming Language :: Python :: 3
Classifier: Programming Language :: Python :: 3.10
Classifier: Programming Language :: Python :: 3.11
Classifier: Programming Language :: Python :: 3.12
Classifier: Operating System :: OS Independent
Requires-Python: >=3.10
Requires-Dist: setuptools>=61.0
Requires-Dist: click>=8.1.7
Requires-Dist: rich>=13.7.1
Requires-Dist: pyyaml>=6.0.1
Requires-Dist: aiohttp>=3.8.0
Requires-Dist: websockets>=12.0
Requires-Dist: jinja2>=3.1.4
Requires-Dist: fastapi>=0.111.1
Requires-Dist: uvicorn[standard]>=0.30.1
Requires-Dist: python-multipart>=0.0.9
Requires-Dist: gitpython>=3.1.43
Requires-Dist: langchain>=0.2.11
Requires-Dist: langchain-community>=0.2.10
Requires-Dist: langchain-openai>=0.1.20
Requires-Dist: langchain-anthropic>=0.1.22
Requires-Dist: langchain-google-genai>=1.0.10
Requires-Dist: langgraph>=0.1.10
Requires-Dist: openai>=1.35.15
Requires-Dist: anthropic>=0.31.0
Requires-Dist: google-generativeai>=0.7.2
Requires-Dist: pydantic>=2.0.0
Requires-Dist: typing-extensions>=4.12.2
Requires-Dist: requests>=2.31.0
Requires-Dist: httpx>=0.27.0
Requires-Dist: aiofiles>=23.2.1
Requires-Dist: sqlalchemy>=2.0.31
Requires-Dist: flask>=3.0.3
Requires-Dist: flask-socketio>=5.3.6
Requires-Dist: websocket-client>=1.8.0
Requires-Dist: fastmcp>=2.0.0
Provides-Extra: dev
Requires-Dist: pytest>=7.0.0; extra == "dev"
Requires-Dist: pytest-cov>=4.0.0; extra == "dev"
Requires-Dist: pytest-asyncio>=0.21.0; extra == "dev"
Requires-Dist: black>=23.0.0; extra == "dev"
Requires-Dist: flake8>=6.0.0; extra == "dev"
Requires-Dist: mypy>=1.0.0; extra == "dev"
Requires-Dist: twine>=4.0.0; extra == "dev"
Provides-Extra: test
Requires-Dist: pytest>=7.0.0; extra == "test"
Requires-Dist: pytest-cov>=4.0.0; extra == "test"
Requires-Dist: pytest-asyncio>=0.21.0; extra == "test"
Provides-Extra: docs
Requires-Dist: sphinx>=5.0.0; extra == "docs"
Requires-Dist: sphinx-rtd-theme>=1.0.0; extra == "docs"
Requires-Dist: autodoc>=0.5.0; extra == "docs"
